polygmsh/__init__.py
polygmsh/__main__.py
polygmsh/core.py
polygmsh-0.1.1.dist-info/METADATA
polygmsh-0.1.1.dist-info/WHEEL
polygmsh-0.1.1.dist-info/entry_points.txt
polygmsh-0.1.1.dist-info/top_level.txt
polygmsh-0.1.1.dist-info/RECORD
